sc_vortex_2d/__init__.py
sc_vortex_2d/data_vortex/__init__.py
sc_vortex_2d/data_vortex/temperature_03/__init__.py
sc_vortex_2d/data_vortex/temperature_03/delta.pkl
sc_vortex_2d/data_vortex/temperature_03/spectra.pkl
sc_vortex_2d/data_vortex/temperature_03/u.pkl
sc_vortex_2d/data_vortex/temperature_03/v.pkl
sc_vortex_2d/data_vortex/temperature_05/__init__.py
sc_vortex_2d/data_vortex/temperature_05/delta.pkl
sc_vortex_2d/data_vortex/temperature_05/spectra.pkl
sc_vortex_2d/data_vortex/temperature_05/u.pkl
sc_vortex_2d/data_vortex/temperature_05/v.pkl
sc_vortex_2d/data_vortex/temperature_08/__init__.py
sc_vortex_2d/data_vortex/temperature_08/delta.pkl
sc_vortex_2d/data_vortex/temperature_08/spectra.pkl
sc_vortex_2d/data_vortex/temperature_08/u.pkl
sc_vortex_2d/data_vortex/temperature_08/v.pkl
sc_vortex_2d/vortex.py
sc_vortex_2d/vortex_instance.py
sc_vortex_2d-1.0.3.dist-info/LICENSE
sc_vortex_2d-1.0.3.dist-info/WHEEL
sc_vortex_2d-1.0.3.dist-info/METADATA
sc_vortex_2d-1.0.3.dist-info/RECORD
