Metadata-Version: 2.1
Name: sc-vortex-2d
Version: 1.0.3
Summary: Numerical result of CdGM mode.
Home-page: https://github.com/ShuN6211/sc-vortex-2d
Author: Shun Makino
Author-email: shunmakino6211@gmail.com
Requires-Python: >=3.9,<3.13
Classifier: Programming Language :: Python :: 3
Classifier: Programming Language :: Python :: 3.9
Classifier: Programming Language :: Python :: 3.10
Classifier: Programming Language :: Python :: 3.11
Requires-Dist: scipy (>=1.10.0,<2.0.0)
Project-URL: Repository, https://github.com/ShuN6211/sc-vortex-2d
